django_enum_intflag_field-0.0.4.dist-info/licenses/LICENSE.txt
enum_intflagfield/__init__.py
enum_intflagfield/enumintflagfield.py
django_enum_intflag_field-0.0.4.dist-info/METADATA
django_enum_intflag_field-0.0.4.dist-info/WHEEL
django_enum_intflag_field-0.0.4.dist-info/top_level.txt
django_enum_intflag_field-0.0.4.dist-info/zip-safe
django_enum_intflag_field-0.0.4.dist-info/RECORD
