Metadata-Version: 2.4
Name: django-enum.IntFlag-field
Version: 0.0.4
Summary: django-enum.IntFlag-field — A model field that takes an enum.IntFlag class, stores flag combinations as an IntegerField, and allows convenient bitwise containment predicates through the Django ORM.
Author-email: nullenenenen <nullenenenen@gavagai.eu>
License: LGPL-3.0+
Project-URL: Homepage, https://sr.ht/~nullenenenen/django-enum.IntFlag-field/
Project-URL: Documentation, https://git.sr.ht/~nullenenenen/django-enum.IntFlag-field/tree/master/item/README.md
Project-URL: Source, https://git.sr.ht/~nullenenenen/django-enum.IntFlag-field/
Keywords: Django,enum.IntFlag,bitfield
Classifier: Development Status :: 4 - Beta
Classifier: Framework :: Django
Classifier: Intended Audience :: Developers
Classifier: License :: OSI Approved :: GNU Lesser General Public License v3 or later (LGPLv3+)
Classifier: Operating System :: OS Independent
Classifier: Topic :: Software Development
Classifier: Topic :: Database
Classifier: Programming Language :: Python :: 3
Requires-Python: >=3.8
License-File: LICENSE.txt
Requires-Dist: Django>=4.2.0
Dynamic: license-file
